pyloges/__init__.py
pyloges/asynclogger.py
pyloges/filename_blanks.py
pyloges/logblanks.py
pyloges/logger.py
pyloges/loglevels.py
pyloges/classes/__init__.py
pyloges/classes/config.py
pyloges/classes/interfaces/__init__.py
pyloges/classes/interfaces/handler.py
pyloges/handlers/__init__.py
pyloges/handlers/file.py
pyloges/handlers/std.py
pyloges-1.1.dist-info/LICENSE
pyloges-1.1.dist-info/METADATA
pyloges-1.1.dist-info/WHEEL
pyloges-1.1.dist-info/top_level.txt
pyloges-1.1.dist-info/RECORD
