Metadata-Version: 2.1
Name: pyloges
Version: 1.1
Summary: Simple and powerful logging library
Home-page: https://github.com/Nekit10/pyloges/
Author: Nikta Serba (Koni Dev Team)
Author-email: nikitaserba@icloud.com
License: GNU GPL v3
Platform: UNKNOWN
